{
  "english": {
    "columns": [
      "Timestamp",
      "Email address",
      "Name and Employee ID",
      "Is the tablet working well for consultations?",
      "Do you face internet problems during consultations?",
      "Do you know how to use the tablet?",
      "If tablet or internet has a problem, do you get help quickly?",
      "Are the doctors nice and respectful during consultations?",
      "Do you face any problems working with the partner staff in the clinic?  ",
      "Are you comfortable with the current clinic timings? ",
      "If not, please tell us what timing changes would help you work better:  ",
      "Are you able to explain doctor’s advice to patients clearly?",
      "Is your clinic clean and in a good condition?",
      "Do you feel safe working alone in the clinic?",
      "Do you get all the medicines you need at the clinic?",
      "Are your DCs and field managers helpful?",
      "Are you able to complete your monthly target?",
      "Do patients behave well with you?",
      "Do patients trust you at the clinic?",
      "Do you get help during health diagnostic camps?",
      "Are all the essential equipment in the clinic working properly?",
      "Do you require any additional training?",
      "Do you feel proud of your work?",
      "Do you feel you can grow in your career while working at M-Swasth? ",
      "Would you tell a friend to work here? (Rate from 1 to 10)",
      "How far is the clinic from your residence? (in meters/ kilometers)",
      "Any additional help you require to work better?",
      "Things that can make your clinic better",
      "Any feedback for the management"
    ],
    "sample": [
      {
        "Timestamp": "2025-05-20 16:41:59.355000",
        "Email address": "mhealthecef532@gmail.com",
        "Name and Employee ID": "Krishnaveni 5774",
        "Is the tablet working well for consultations?": "Yes",
        "Do you face internet problems during consultations?": "Sometimes",
        "Do you know how to use the tablet?": "Yes",
        "If tablet or internet has a problem, do you get help quickly?": "Yes",
        "Are the doctors nice and respectful during consultations?": "Yes",
        "Do you face any problems working with the partner staff in the clinic?  ": "No",
        "Are you comfortable with the current clinic timings? ": "Yes",
        "If not, please tell us what timing changes would help you work better:  ": NaN,
        "Are you able to explain doctor’s advice to patients clearly?": "Yes",
        "Is your clinic clean and in a good condition?": "Yes",
        "Do you feel safe working alone in the clinic?": "Yes",
        "Do you get all the medicines you need at the clinic?": "Yes",
        "Are your DCs and field managers helpful?": "Yes",
        "Are you able to complete your monthly target?": "Sometimes",
        "Do patients behave well with you?": "Yes",
        "Do patients trust you at the clinic?": "Yes",
        "Do you get help during health diagnostic camps?": "Yes",
        "Are all the essential equipment in the clinic working properly?": "Yes",
        "Do you require any additional training?": "Maybe later",
        "Do you feel proud of your work?": "Yes",
        "Do you feel you can grow in your career while working at M-Swasth? ": "Yes",
        "Would you tell a friend to work here? (Rate from 1 to 10)": 9,
        "How far is the clinic from your residence? (in meters/ kilometers)": "Kilometres ",
        "Any additional help you require to work better?": "No",
        "Things that can make your clinic better": "No",
        "Any feedback for the management": "No"
      },
      {
        "Timestamp": "2025-05-20 16:48:49.693000",
        "Email address": "mhealthecpp010@gmail.com",
        "Name and Employee ID": "Rekha Sharma  1395",
        "Is the tablet working well for consultations?": "Yes",
        "Do you face internet problems during consultations?": "No",
        "Do you know how to use the tablet?": "Yes",
        "If tablet or internet has a problem, do you get help quickly?": "Yes",
        "Are the doctors nice and respectful during consultations?": "Yes",
        "Do you face any problems working with the partner staff in the clinic?  ": "No",
        "Are you comfortable with the current clinic timings? ": "Yes",
        "If not, please tell us what timing changes would help you work better:  ": " 9 am to 4 pm better  in summer time ",
        "Are you able to explain doctor’s advice to patients clearly?": "Yes",
        "Is your clinic clean and in a good condition?": "Yes",
        "Do you feel safe working alone in the clinic?": "Yes",
        "Do you get all the medicines you need at the clinic?": "Yes",
        "Are your DCs and field managers helpful?": "Yes",
        "Are you able to complete your monthly target?": "Yes",
        "Do patients behave well with you?": "Yes",
        "Do patients trust you at the clinic?": "Yes",
        "Do you get help during health diagnostic camps?": "Sometimes",
        "Are all the essential equipment in the clinic working properly?": "Yes",
        "Do you require any additional training?": "No",
        "Do you feel proud of your work?": "Yes",
        "Do you feel you can grow in your career while working at M-Swasth? ": "Yes",
        "Would you tell a friend to work here? (Rate from 1 to 10)": 10,
        "How far is the clinic from your residence? (in meters/ kilometers)": "7 km",
        "Any additional help you require to work better?": "Yes field visit ke liye mujhe bm ya dure staf ki help chaiye",
        "Things that can make your clinic better": "1 bar ke liye field visit pe medicine deni chaiye taki pt ko aram mile or next time clinic aye",
        "Any feedback for the management": "all is well "
      },
      {
        "Timestamp": "2025-05-20 17:00:33.372000",
        "Email address": "mhealthecp009@gmail.com",
        "Name and Employee ID": "Kamni Kumari (1814)",
        "Is the tablet working well for consultations?": "Yes",
        "Do you face internet problems during consultations?": "Sometimes",
        "Do you know how to use the tablet?": "Yes",
        "If tablet or internet has a problem, do you get help quickly?": "Yes",
        "Are the doctors nice and respectful during consultations?": "Yes",
        "Do you face any problems working with the partner staff in the clinic?  ": "Yes",
        "Are you comfortable with the current clinic timings? ": "Yes",
        "If not, please tell us what timing changes would help you work better:  ": "No",
        "Are you able to explain doctor’s advice to patients clearly?": "Yes",
        "Is your clinic clean and in a good condition?": "Yes",
        "Do you feel safe working alone in the clinic?": "Yes",
        "Do you get all the medicines you need at the clinic?": "Yes",
        "Are your DCs and field managers helpful?": "Yes",
        "Are you able to complete your monthly target?": "Yes",
        "Do patients behave well with you?": "Yes",
        "Do patients trust you at the clinic?": "Yes",
        "Do you get help during health diagnostic camps?": "Yes",
        "Are all the essential equipment in the clinic working properly?": "Yes",
        "Do you require any additional training?": "Yes",
        "Do you feel proud of your work?": "Yes",
        "Do you feel you can grow in your career while working at M-Swasth? ": "No",
        "Would you tell a friend to work here? (Rate from 1 to 10)": 10,
        "How far is the clinic from your residence? (in meters/ kilometers)": "No",
        "Any additional help you require to work better?": "2-3chair",
        "Things that can make your clinic better": "No",
        "Any feedback for the management": "No issues "
      }
    ],
    "dtypes": {
      "Timestamp": "datetime64[ns]",
      "Email address": "object",
      "Name and Employee ID": "object",
      "Is the tablet working well for consultations?": "object",
      "Do you face internet problems during consultations?": "object",
      "Do you know how to use the tablet?": "object",
      "If tablet or internet has a problem, do you get help quickly?": "object",
      "Are the doctors nice and respectful during consultations?": "object",
      "Do you face any problems working with the partner staff in the clinic?  ": "object",
      "Are you comfortable with the current clinic timings? ": "object",
      "If not, please tell us what timing changes would help you work better:  ": "object",
      "Are you able to explain doctor’s advice to patients clearly?": "object",
      "Is your clinic clean and in a good condition?": "object",
      "Do you feel safe working alone in the clinic?": "object",
      "Do you get all the medicines you need at the clinic?": "object",
      "Are your DCs and field managers helpful?": "object",
      "Are you able to complete your monthly target?": "object",
      "Do patients behave well with you?": "object",
      "Do patients trust you at the clinic?": "object",
      "Do you get help during health diagnostic camps?": "object",
      "Are all the essential equipment in the clinic working properly?": "object",
      "Do you require any additional training?": "object",
      "Do you feel proud of your work?": "object",
      "Do you feel you can grow in your career while working at M-Swasth? ": "object",
      "Would you tell a friend to work here? (Rate from 1 to 10)": "int64",
      "How far is the clinic from your residence? (in meters/ kilometers)": "object",
      "Any additional help you require to work better?": "object",
      "Things that can make your clinic better": "object",
      "Any feedback for the management": "object"
    }
  },
  "hindi": {
    "columns": [
      "Timestamp",
      "Email address",
      "नाम  और  Employee ID ",
      "क्या टैबलेट डॉक्टर से बात करने के लिए ठीक से काम कर रहा है? ",
      "क्या आपको डॉक्टर से बात करते समय इंटरनेट संबंधी समस्याओं का सामना करना पड़ता है? ",
      "क्या आप टैबलेट का उपयोग करना जानते हैं? ",
      "यदि टैबलेट या इंटरनेट में कोई समस्या आती है तो क्या आपको तुरंत सहायता मिल जाती है? ",
      "क्या डॉक्टर वीडियो कॉल पर अच्छे और सम्मानजनक हैं? ",
      "क्या आप मरीज़ को डॉक्टर की सलाह स्पष्ट रूप से समझा सकते हैं? ",
      "क्या आपका क्लिनिक साफ-सुथरा और अच्छी स्थिति में है? ",
      "क्या पंखे,और लाइट सही से काम करते हैं?",
      "क्या आप क्लिनिक में अकेले काम करते हुए सुरक्षित महसूस करते हैं? ",
      "क्या आपको क्लिनिक में सभी आवश्यक दवाइयां मिल जाती हैं? ",
      "क्या आपका डीसी या फील्ड मैनेजर मददगार है? ",
      "क्या आप अपना मासिक लक्ष्य पूरा कर पाते हैं? ",
      "क्या मरीज़ आपके साथ अच्छा व्यवहार करते हैं? ",
      "क्या मरीज़ क्लिनिक में आप पर भरोसा करते हैं? ",
      "क्या आपको हेल्थ डायग्नोस्टिक कैंप्स के दौरान सहायता मिलती है? ",
      "क्या आपको क्लिनिक में पार्टनर स्टाफ के साथ काम करने में कोई समस्या होती है?",
      "क्या आप क्लिनिक के समय से संतुष्ट हैं?",
      "यदि नहीं, तो कृपया हमें बताएं कि क्लिनिक के समय में क्या बदलाव आपके कार्य को बेहतर बनाने में मदद करेंगे?",
      "क्या आपको टैबलेट का उपयोग करने और क्लिनिक में काम करने का प्रशिक्षण मिला था? ",
      "क्या आपको किसी अतिरिक्त प्रशिक्षण की आवश्यकता है? ",
      "क्या आपको अपने काम पर गर्व महसूस होता है? ",
      "क्या आप अपने किसी मित्र को यहां काम करने के लिए कहेंगे? (1 से 10 तक रेटिंग दें) ",
      "क्या आप एम-स्वस्थ में काम करते हुए अपने करियर में आगे बढ़ पा रहे हैं? ",
      "क्या आपको बेहतर काम करने के लिए किसी अतिरिक्त सहायता की आवश्यकता है? ",
      "ऐसी चीजें जो आपके क्लिनिक को बेहतर बना सकती हैं: ",
      "प्रबंधन को कोई प्रतिक्रिया: "
    ],
    "sample": [
      {
        "Timestamp": " ",
        "Email address": "nkridant@gmail.com",
        "नाम  और  Employee ID ": "ecmt 384 Nikita ",
        "क्या टैबलेट डॉक्टर से बात करने के लिए ठीक से काम कर रहा है? ": "नहीं",
        "क्या आपको डॉक्टर से बात करते समय इंटरनेट संबंधी समस्याओं का सामना करना पड़ता है? ": "हाँ",
        "क्या आप टैबलेट का उपयोग करना जानते हैं? ": "हाँ",
        "यदि टैबलेट या इंटरनेट में कोई समस्या आती है तो क्या आपको तुरंत सहायता मिल जाती है? ": "हाँ",
        "क्या डॉक्टर वीडियो कॉल पर अच्छे और सम्मानजनक हैं? ": "हाँ",
        "क्या आप मरीज़ को डॉक्टर की सलाह स्पष्ट रूप से समझा सकते हैं? ": "हाँ",
        "क्या आपका क्लिनिक साफ-सुथरा और अच्छी स्थिति में है? ": "हाँ",
        "क्या पंखे,और लाइट सही से काम करते हैं?": "हाँ",
        "क्या आप क्लिनिक में अकेले काम करते हुए सुरक्षित महसूस करते हैं? ": "हाँ",
        "क्या आपको क्लिनिक में सभी आवश्यक दवाइयां मिल जाती हैं? ": "हाँ",
        "क्या आपका डीसी या फील्ड मैनेजर मददगार है? ": "हाँ",
        "क्या आप अपना मासिक लक्ष्य पूरा कर पाते हैं? ": "कभी-कभी",
        "क्या मरीज़ आपके साथ अच्छा व्यवहार करते हैं? ": "हाँ",
        "क्या मरीज़ क्लिनिक में आप पर भरोसा करते हैं? ": "हाँ",
        "क्या आपको हेल्थ डायग्नोस्टिक कैंप्स के दौरान सहायता मिलती है? ": "हाँ",
        "क्या आपको क्लिनिक में पार्टनर स्टाफ के साथ काम करने में कोई समस्या होती है?": "नहीं",
        "क्या आप क्लिनिक के समय से संतुष्ट हैं?": "नहीं",
        "यदि नहीं, तो कृपया हमें बताएं कि क्लिनिक के समय में क्या बदलाव आपके कार्य को बेहतर बनाने में मदद करेंगे?": NaN,
        "क्या आपको टैबलेट का उपयोग करने और क्लिनिक में काम करने का प्रशिक्षण मिला था? ": "हाँ",
        "क्या आपको किसी अतिरिक्त प्रशिक्षण की आवश्यकता है? ": "शायद बाद में",
        "क्या आपको अपने काम पर गर्व महसूस होता है? ": "हाँ",
        "क्या आप अपने किसी मित्र को यहां काम करने के लिए कहेंगे? (1 से 10 तक रेटिंग दें) ": 10,
        "क्या आप एम-स्वस्थ में काम करते हुए अपने करियर में आगे बढ़ पा रहे हैं? ": "हाँ",
        "क्या आपको बेहतर काम करने के लिए किसी अतिरिक्त सहायता की आवश्यकता है? ": "ha",
        "ऐसी चीजें जो आपके क्लिनिक को बेहतर बना सकती हैं: ": "Ha",
        "प्रबंधन को कोई प्रतिक्रिया: ": "medicine me improve karna..tab fast work nhi karta esliye mobile se work karna padta hai., sallery kami kar di hai o phile jaise kar dijiye,"
      },
      {
        "Timestamp": "2025-05-20 16:35:03.420000",
        "Email address": "dikshachoudhary529@gmail.com",
        "नाम  और  Employee ID ": "Diksha 6170",
        "क्या टैबलेट डॉक्टर से बात करने के लिए ठीक से काम कर रहा है? ": "हाँ",
        "क्या आपको डॉक्टर से बात करते समय इंटरनेट संबंधी समस्याओं का सामना करना पड़ता है? ": "नहीं",
        "क्या आप टैबलेट का उपयोग करना जानते हैं? ": "हाँ",
        "यदि टैबलेट या इंटरनेट में कोई समस्या आती है तो क्या आपको तुरंत सहायता मिल जाती है? ": "कभी-कभी",
        "क्या डॉक्टर वीडियो कॉल पर अच्छे और सम्मानजनक हैं? ": "हाँ",
        "क्या आप मरीज़ को डॉक्टर की सलाह स्पष्ट रूप से समझा सकते हैं? ": "हाँ",
        "क्या आपका क्लिनिक साफ-सुथरा और अच्छी स्थिति में है? ": "हाँ",
        "क्या पंखे,और लाइट सही से काम करते हैं?": "हाँ",
        "क्या आप क्लिनिक में अकेले काम करते हुए सुरक्षित महसूस करते हैं? ": "हाँ",
        "क्या आपको क्लिनिक में सभी आवश्यक दवाइयां मिल जाती हैं? ": "हाँ",
        "क्या आपका डीसी या फील्ड मैनेजर मददगार है? ": "हाँ",
        "क्या आप अपना मासिक लक्ष्य पूरा कर पाते हैं? ": "हाँ",
        "क्या मरीज़ आपके साथ अच्छा व्यवहार करते हैं? ": "हाँ",
        "क्या मरीज़ क्लिनिक में आप पर भरोसा करते हैं? ": "हाँ",
        "क्या आपको हेल्थ डायग्नोस्टिक कैंप्स के दौरान सहायता मिलती है? ": "हाँ",
        "क्या आपको क्लिनिक में पार्टनर स्टाफ के साथ काम करने में कोई समस्या होती है?": "नहीं",
        "क्या आप क्लिनिक के समय से संतुष्ट हैं?": "हाँ",
        "यदि नहीं, तो कृपया हमें बताएं कि क्लिनिक के समय में क्या बदलाव आपके कार्य को बेहतर बनाने में मदद करेंगे?": NaN,
        "क्या आपको टैबलेट का उपयोग करने और क्लिनिक में काम करने का प्रशिक्षण मिला था? ": "हाँ",
        "क्या आपको किसी अतिरिक्त प्रशिक्षण की आवश्यकता है? ": "नहीं",
        "क्या आपको अपने काम पर गर्व महसूस होता है? ": "हाँ",
        "क्या आप अपने किसी मित्र को यहां काम करने के लिए कहेंगे? (1 से 10 तक रेटिंग दें) ": 7,
        "क्या आप एम-स्वस्थ में काम करते हुए अपने करियर में आगे बढ़ पा रहे हैं? ": "हाँ",
        "क्या आपको बेहतर काम करने के लिए किसी अतिरिक्त सहायता की आवश्यकता है? ": "Yes",
        "ऐसी चीजें जो आपके क्लिनिक को बेहतर बना सकती हैं: ": "Lab facilities ",
        "प्रबंधन को कोई प्रतिक्रिया: ": "No"
      },
      {
        "Timestamp": "2025-05-20 16:35:48.479000",
        "Email address": "kapoorkanchan16@gmail.com",
        "नाम  और  Employee ID ": "Kanchan Ecsmp 543",
        "क्या टैबलेट डॉक्टर से बात करने के लिए ठीक से काम कर रहा है? ": "हाँ",
        "क्या आपको डॉक्टर से बात करते समय इंटरनेट संबंधी समस्याओं का सामना करना पड़ता है? ": "हाँ",
        "क्या आप टैबलेट का उपयोग करना जानते हैं? ": "हाँ",
        "यदि टैबलेट या इंटरनेट में कोई समस्या आती है तो क्या आपको तुरंत सहायता मिल जाती है? ": "हाँ",
        "क्या डॉक्टर वीडियो कॉल पर अच्छे और सम्मानजनक हैं? ": "हाँ",
        "क्या आप मरीज़ को डॉक्टर की सलाह स्पष्ट रूप से समझा सकते हैं? ": "हाँ",
        "क्या आपका क्लिनिक साफ-सुथरा और अच्छी स्थिति में है? ": "हाँ",
        "क्या पंखे,और लाइट सही से काम करते हैं?": "हाँ",
        "क्या आप क्लिनिक में अकेले काम करते हुए सुरक्षित महसूस करते हैं? ": "हाँ",
        "क्या आपको क्लिनिक में सभी आवश्यक दवाइयां मिल जाती हैं? ": "हाँ",
        "क्या आपका डीसी या फील्ड मैनेजर मददगार है? ": "हाँ",
        "क्या आप अपना मासिक लक्ष्य पूरा कर पाते हैं? ": "हाँ",
        "क्या मरीज़ आपके साथ अच्छा व्यवहार करते हैं? ": "हाँ",
        "क्या मरीज़ क्लिनिक में आप पर भरोसा करते हैं? ": "हाँ",
        "क्या आपको हेल्थ डायग्नोस्टिक कैंप्स के दौरान सहायता मिलती है? ": "हाँ",
        "क्या आपको क्लिनिक में पार्टनर स्टाफ के साथ काम करने में कोई समस्या होती है?": "हाँ",
        "क्या आप क्लिनिक के समय से संतुष्ट हैं?": "हाँ",
        "यदि नहीं, तो कृपया हमें बताएं कि क्लिनिक के समय में क्या बदलाव आपके कार्य को बेहतर बनाने में मदद करेंगे?": "All is good ..D.C sir also coperative...and manage all thig property ",
        "क्या आपको टैबलेट का उपयोग करने और क्लिनिक में काम करने का प्रशिक्षण मिला था? ": "हाँ",
        "क्या आपको किसी अतिरिक्त प्रशिक्षण की आवश्यकता है? ": "हाँ",
        "क्या आपको अपने काम पर गर्व महसूस होता है? ": "हाँ",
        "क्या आप अपने किसी मित्र को यहां काम करने के लिए कहेंगे? (1 से 10 तक रेटिंग दें) ": 10,
        "क्या आप एम-स्वस्थ में काम करते हुए अपने करियर में आगे बढ़ पा रहे हैं? ": "हाँ",
        "क्या आपको बेहतर काम करने के लिए किसी अतिरिक्त सहायता की आवश्यकता है? ": "No",
        "ऐसी चीजें जो आपके क्लिनिक को बेहतर बना सकती हैं: ": ".",
        "प्रबंधन को कोई प्रतिक्रिया: ": 8091710858
      }
    ],
    "dtypes": {
      "Timestamp": "object",
      "Email address": "object",
      "नाम  और  Employee ID ": "object",
      "क्या टैबलेट डॉक्टर से बात करने के लिए ठीक से काम कर रहा है? ": "object",
      "क्या आपको डॉक्टर से बात करते समय इंटरनेट संबंधी समस्याओं का सामना करना पड़ता है? ": "object",
      "क्या आप टैबलेट का उपयोग करना जानते हैं? ": "object",
      "यदि टैबलेट या इंटरनेट में कोई समस्या आती है तो क्या आपको तुरंत सहायता मिल जाती है? ": "object",
      "क्या डॉक्टर वीडियो कॉल पर अच्छे और सम्मानजनक हैं? ": "object",
      "क्या आप मरीज़ को डॉक्टर की सलाह स्पष्ट रूप से समझा सकते हैं? ": "object",
      "क्या आपका क्लिनिक साफ-सुथरा और अच्छी स्थिति में है? ": "object",
      "क्या पंखे,और लाइट सही से काम करते हैं?": "object",
      "क्या आप क्लिनिक में अकेले काम करते हुए सुरक्षित महसूस करते हैं? ": "object",
      "क्या आपको क्लिनिक में सभी आवश्यक दवाइयां मिल जाती हैं? ": "object",
      "क्या आपका डीसी या फील्ड मैनेजर मददगार है? ": "object",
      "क्या आप अपना मासिक लक्ष्य पूरा कर पाते हैं? ": "object",
      "क्या मरीज़ आपके साथ अच्छा व्यवहार करते हैं? ": "object",
      "क्या मरीज़ क्लिनिक में आप पर भरोसा करते हैं? ": "object",
      "क्या आपको हेल्थ डायग्नोस्टिक कैंप्स के दौरान सहायता मिलती है? ": "object",
      "क्या आपको क्लिनिक में पार्टनर स्टाफ के साथ काम करने में कोई समस्या होती है?": "object",
      "क्या आप क्लिनिक के समय से संतुष्ट हैं?": "object",
      "यदि नहीं, तो कृपया हमें बताएं कि क्लिनिक के समय में क्या बदलाव आपके कार्य को बेहतर बनाने में मदद करेंगे?": "object",
      "क्या आपको टैबलेट का उपयोग करने और क्लिनिक में काम करने का प्रशिक्षण मिला था? ": "object",
      "क्या आपको किसी अतिरिक्त प्रशिक्षण की आवश्यकता है? ": "object",
      "क्या आपको अपने काम पर गर्व महसूस होता है? ": "object",
      "क्या आप अपने किसी मित्र को यहां काम करने के लिए कहेंगे? (1 से 10 तक रेटिंग दें) ": "int64",
      "क्या आप एम-स्वस्थ में काम करते हुए अपने करियर में आगे बढ़ पा रहे हैं? ": "object",
      "क्या आपको बेहतर काम करने के लिए किसी अतिरिक्त सहायता की आवश्यकता है? ": "object",
      "ऐसी चीजें जो आपके क्लिनिक को बेहतर बना सकती हैं: ": "object",
      "प्रबंधन को कोई प्रतिक्रिया: ": "object"
    }
  }
}